Workbook

Sheet Comece aqui
B2: Modelo integrado simplificado: DRE, Balanço e Fluxo de Caixa
B3: Mude as premissas e veja os três demonstrativos se moverem juntos. Se o Balanço não fechar, a aba Checagem avisa.
B6: Como usar
B7: 1 | C7: Vá na aba Premissas e mude só as células azuis (receita, crescimento, custos, prazos...).
B8: 2 | C8: Acompanhe a DRE, o Balanço e o Fluxo de Caixa. Nenhuma outra célula precisa ser digitada.
B9: 3 | C9: Confira a aba Checagem: a diferença do Balanço tem que ser zero em todos os anos.
B11: Cores das células
B12: ■ | C12: Azul: premissa. É o único lugar onde você digita.
B13: ■ | C13: Preto: fórmula calculada na própria aba.
B14: ■ | C14: Verde: número que vem de outra aba. É aqui que os demonstrativos se conectam.
B16: O que este modelo deixa de fora, de propósito
B17: • | C17: Dívida e juros (e o efeito deles no caixa e no lucro)
B18: • | C18: Dividendos e distribuição de lucro
B19: • | C19: Estoques e o ciclo de caixa completo
B20: • | C20: Cenários e análise de sensibilidade
C21: No curso Fundamentos da Modelagem Financeira você adiciona cada uma dessas peças sem quebrar o modelo.
C23: Conheça o curso Fundamentos da Modelagem Financeira →
C25: Valores em R$ mil. Empresa-exemplo, sem dívida, para focar na ligação entre os demonstrativos.
C26: Modelagem Financeira na Prática · mfnapratica.com.br

Sheet Premissas
B2: Premissas
B3: Mude só as células azuis. Valores em R$ mil.
B6: Operação
B7: Receita no ano 1 | C7: 1000 | D7: Faturamento líquido do primeiro ano
B8: Crescimento da receita por ano | C8: 0.1 | D8: Aplicado nos anos 2 e 3
B9: Custos (% da receita) | C9: 0.6 | D9: Custo dos produtos ou serviços vendidos
B10: Despesas (% da receita) | C10: 0.2 | D10: Vendas, gerais e administrativas
B11: Depreciação por ano | C11: 50 | D11: Reduz o lucro, mas não sai do caixa
B12: Investimento por ano (capex) | C12: 60 | D12: Compra de máquinas e equipamentos
B13: Alíquota de IR | C13: 0.3 | D13: Sobre o lucro antes do imposto
B15: Capital de giro
B16: Prazo de recebimento dos clientes (dias) | C16: 30 | D16: Vendas que ainda não viraram caixa
B17: Prazo de pagamento aos fornecedores (dias) | C17: 30 | D17: Custos que ainda não saíram do caixa
B19: Saldos iniciais (Balanço do ano 0)
B20: Caixa | C20: 100
B21: Imobilizado | C21: 500
B22: Patrimônio líquido | C22: 600 | D22: Ativo = Passivo + PL já no ano 0

Sheet DRE
B2: DRE (Demonstração do Resultado)
B3: R$ mil. O lucro líquido vai para o Patrimônio líquido (Balanço) e para o Fluxo de Caixa.
C5: Ano 0 | D5: Ano 1 | E5: Ano 2 | F5: Ano 3
B6: Receita líquida | D6: =Premissas!$C$7 | E6: =D6*(1+Premissas!$C$8) | F6: =E6*(1+Premissas!$C$8)
B7: (−) Custos | D7: =-D6*Premissas!$C$9 | E7: =-E6*Premissas!$C$9 | F7: =-F6*Premissas!$C$9
B8: Lucro bruto | D8: =D6+D7 | E8: =E6+E7 | F8: =F6+F7
B9: (−) Despesas | D9: =-D6*Premissas!$C$10 | E9: =-E6*Premissas!$C$10 | F9: =-F6*Premissas!$C$10
B10: EBITDA | D10: =D8+D9 | E10: =E8+E9 | F10: =F8+F9
B11: (−) Depreciação | D11: =-Premissas!$C$11 | E11: =-Premissas!$C$11 | F11: =-Premissas!$C$11
B12: EBIT (lucro operacional) | D12: =D10+D11 | E12: =E10+E11 | F12: =F10+F11
B13: (−) IR | D13: =-MAX(0,D12)*Premissas!$C$13 | E13: =-MAX(0,E12)*Premissas!$C$13 | F13: =-MAX(0,F12)*Premissas!$C$13
B14: Lucro líquido | D14: =D12+D13 | E14: =E12+E13 | F14: =F12+F13

Sheet Balanço
B2: Balanço Patrimonial
B3: R$ mil. O caixa vem do Fluxo de Caixa; o patrimônio soma o lucro da DRE.
B5: Ativo | C5: Ano 0 | D5: Ano 1 | E5: Ano 2 | F5: Ano 3
B6: Caixa | C6: =Premissas!$C$20 | D6: ='Fluxo de Caixa'!D14 | E6: ='Fluxo de Caixa'!E14 | F6: ='Fluxo de Caixa'!F14
B7: Contas a receber | C7: 0 | D7: =DRE!D6*Premissas!$C$16/360 | E7: =DRE!E6*Premissas!$C$16/360 | F7: =DRE!F6*Premissas!$C$16/360
B8: Imobilizado | C8: =Premissas!$C$21 | D8: =C8+Premissas!$C$12-Premissas!$C$11 | E8: =D8+Premissas!$C$12-Premissas!$C$11 | F8: =E8+Premissas!$C$12-Premissas!$C$11
B9: Ativo total | C9: =SUM(C6:C8) | D9: =SUM(D6:D8) | E9: =SUM(E6:E8) | F9: =SUM(F6:F8)
B11: Passivo e patrimônio líquido | C11: Ano 0 | D11: Ano 1 | E11: Ano 2 | F11: Ano 3
B12: Fornecedores | C12: 0 | D12: =-DRE!D7*Premissas!$C$17/360 | E12: =-DRE!E7*Premissas!$C$17/360 | F12: =-DRE!F7*Premissas!$C$17/360
B13: Patrimônio líquido | C13: =Premissas!$C$22 | D13: =C13+DRE!D14 | E13: =D13+DRE!E14 | F13: =E13+DRE!F14
B14: Passivo + PL | C14: =C12+C13 | D14: =D12+D13 | E14: =E12+E13 | F14: =F12+F13
B16: Checagem: Ativo − (Passivo + PL) | C16: =ROUND(C9-C14,6) | D16: =ROUND(D9-D14,6) | E16: =ROUND(E9-E14,6) | F16: =ROUND(F9-F14,6)

Sheet Fluxo de Caixa
B2: Fluxo de Caixa (método indireto)
B3: R$ mil. Parte do lucro e explica por que o caixa não é igual ao lucro.
D5: Ano 1 | E5: Ano 2 | F5: Ano 3
B6: Lucro líquido | D6: =DRE!D14 | E6: =DRE!E14 | F6: =DRE!F14
B7: (+) Depreciação | D7: =-DRE!D11 | E7: =-DRE!E11 | F7: =-DRE!F11
B8: (−) Aumento de contas a receber | D8: =-(Balanço!D7-Balanço!C7) | E8: =-(Balanço!E7-Balanço!D7) | F8: =-(Balanço!F7-Balanço!E7)
B9: (+) Aumento de fornecedores | D9: =Balanço!D12-Balanço!C12 | E9: =Balanço!E12-Balanço!D12 | F9: =Balanço!F12-Balanço!E12
B10: Caixa das operações | D10: =SUM(D6:D9) | E10: =SUM(E6:E9) | F10: =SUM(F6:F9)
B11: (−) Investimentos (capex) | D11: =-Premissas!$C$12 | E11: =-Premissas!$C$12 | F11: =-Premissas!$C$12
B12: Variação do caixa | D12: =D10+D11 | E12: =E10+E11 | F12: =F10+F11
B13: Caixa inicial | D13: =Balanço!C6 | E13: =Balanço!D6 | F13: =Balanço!E6
B14: Caixa final | D14: =D13+D12 | E14: =E13+E12 | F14: =F13+F12

Sheet Checagem
B2: Checagem
B3: Tudo zero = o modelo fecha. Qualquer número diferente de zero aponta uma ligação quebrada.
C5: Ano 0 | D5: Ano 1 | E5: Ano 2 | F5: Ano 3
B6: Ativo − (Passivo + PL) | C6: =Balanço!C16 | D6: =Balanço!D16 | E6: =Balanço!E16 | F6: =Balanço!F16
B7: Caixa do Fluxo de Caixa − Caixa do Balanço | D7: =ROUND('Fluxo de Caixa'!D14-Balanço!D6,6) | E7: =ROUND('Fluxo de Caixa'!E14-Balanço!E6,6) | F7: =ROUND('Fluxo de Caixa'!F14-Balanço!F6,6)
B8: Situação | C8: =IF(AND(ABS(C6)<0.01,ABS(N(C7))<0.01),"Fecha","Não fecha") | D8: =IF(AND(ABS(D6)<0.01,ABS(N(D7))<0.01),"Fecha","Não fecha") | E8: =IF(AND(ABS(E6)<0.01,ABS(N(E7))<0.01),"Fecha","Não fecha") | F8: =IF(AND(ABS(F6)<0.01,ABS(N(F7))<0.01),"Fecha","Não fecha")
B10: Resultado do modelo | C10: =IF(COUNTIF(C8:F8,"Fecha")=4,"✓ O modelo fecha nos 3 anos","✗ Há uma ligação quebrada")
